hpc_aligners/__init__.py
hpc_aligners/hpc_aligners.py
hpc_aligners-1.2.0.dist-info/LICENSE
hpc_aligners-1.2.0.dist-info/METADATA
hpc_aligners-1.2.0.dist-info/WHEEL
hpc_aligners-1.2.0.dist-info/top_level.txt
hpc_aligners-1.2.0.dist-info/RECORD
